easedate/__init__.py
easedate/easedate.py
tests/__init__.py
tests/easedate_test.py
easedate-0.0.3.dist-info/LICENSE
easedate-0.0.3.dist-info/METADATA
easedate-0.0.3.dist-info/WHEEL
easedate-0.0.3.dist-info/top_level.txt
easedate-0.0.3.dist-info/RECORD
