Metadata-Version: 2.1
Name: easedate
Version: 0.0.3
Summary: A python package for easy date use and conversions.
Home-page: https://github.com/brworkit/python-package-easedate.git
Author: brworkit
Author-email: brworkit@gmail.com
License: UNKNOWN
Platform: UNKNOWN
Classifier: Programming Language :: Python :: 3
Classifier: License :: OSI Approved :: MIT License
Classifier: Operating System :: OS Independent
Requires-Python: >=3.6
